gpxpy/__init__.py
gpxpy/geo.py
gpxpy/gpx.py
gpxpy/gpxfield.py
gpxpy/gpxxml.py
gpxpy/parser.py
gpxpy/py.typed
gpxpy/utils.py
gpxpy-1.6.0.data/scripts/gpxinfo
gpxpy-1.6.0.dist-info/LICENSE.txt
gpxpy-1.6.0.dist-info/METADATA
gpxpy-1.6.0.dist-info/NOTICE.txt
gpxpy-1.6.0.dist-info/WHEEL
gpxpy-1.6.0.dist-info/top_level.txt
gpxpy-1.6.0.dist-info/RECORD
