Metadata-Version: 2.1
Name: gpxpy
Version: 1.6.0
Summary: GPX file parser and GPS track manipulation library
Home-page: https://github.com/tkrajina/gpxpy
Author: Tomo Krajina
Author-email: tkrajina@gmail.com
License: Apache License, Version 2.0
Classifier: Programming Language :: Python
Classifier: Programming Language :: Python :: 3.6
Classifier: Programming Language :: Python :: 3.7
Classifier: Programming Language :: Python :: 3.8
Requires-Python: >=3.6
License-File: LICENSE.txt
License-File: NOTICE.txt
